shil/__init__.py
shil/__main__.py
shil/_version.py
shil/bin.py
shil/console.py
shil/util.py
shil/models/__init__.py
shil/models/base.py
shil/models/docker.py
shil/parser/__init__.py
shil/parser/grammar.py
shil/parser/semantics.py
shil-2025.8.6.5.22.dist-info/METADATA
shil-2025.8.6.5.22.dist-info/WHEEL
shil-2025.8.6.5.22.dist-info/top_level.txt
shil-2025.8.6.5.22.dist-info/RECORD
