Metadata-Version: 2.4
Name: shil
Version: 2025.8.6.5.22
Summary: Shell helper utilities for python
Home-page: https://github.com/elo-enterprises/shil/
Author: elo
License: MIT
Project-URL: Documentation, https://github.com/elo-enterprises/shil/
Project-URL: Source, https://github.com/elo-enterprises/shil/
Project-URL: Download, https://github.com/elo-enterprises/shil/#files
Platform: any
Classifier: Programming Language :: Python
Requires-Python: >3.7
Requires-Dist: TatSu==5.8.3
Requires-Dist: pydantic>=2
Requires-Dist: fleks==2025.8.6.4.1
Requires-Dist: python-on-whales==0.71.0
Provides-Extra: dev
Requires-Dist: tox; extra == "dev"
Requires-Dist: IPython; extra == "dev"
Provides-Extra: repl
Requires-Dist: IPython; extra == "repl"
Provides-Extra: testing
Requires-Dist: pytest; extra == "testing"
Requires-Dist: pytest-cov; extra == "testing"
Requires-Dist: mock; extra == "testing"
Requires-Dist: flake8==5.0.4; extra == "testing"
Provides-Extra: lint
Requires-Dist: tox; extra == "lint"
Provides-Extra: publish
Requires-Dist: twine; extra == "publish"
